rsp1570serial/__init__.py
rsp1570serial/connection.py
rsp1570serial/discovery.py
rsp1570serial/emulator.py
rsp1570serial/icons.py
rsp1570serial/message_types.py
rsp1570serial/messages.py
rsp1570serial/process_command.py
rsp1570serial/protocol.py
rsp1570serial/py.typed
rsp1570serial/rotel_model_meta.py
rsp1570serial/rsp1570_messages.py
rsp1570serial/rsp1572_messages.py
rsp1570serial/utils.py
rsp1570serial_pp81381-1.0.1.dist-info/licenses/LICENSE
tests/__init__.py
tests/emulator_test_helper.py
tests/test_commands.py
tests/test_connection.py
tests/test_discovery.py
tests/test_emulator.py
tests/test_icons.py
tests/test_messages.py
tests/test_process_command.py
tests/test_protocol.py
rsp1570serial_pp81381-1.0.1.dist-info/METADATA
rsp1570serial_pp81381-1.0.1.dist-info/WHEEL
rsp1570serial_pp81381-1.0.1.dist-info/top_level.txt
rsp1570serial_pp81381-1.0.1.dist-info/RECORD
