Metadata-Version: 2.4
Name: rsp1570serial-pp81381
Version: 1.0.1
Summary: Rotel RSP-1570 or RSP-1572 processor asyncio RS-232 protocol
Home-page: https://github.com/pp81381/rsp1570serial
Author: Phil Porter
Classifier: Programming Language :: Python :: 3.9
Classifier: Programming Language :: Python :: 3.10
Classifier: Programming Language :: Python :: 3.11
Classifier: Programming Language :: Python :: 3.12
Classifier: License :: OSI Approved :: MIT License
Classifier: Operating System :: OS Independent
Classifier: Topic :: Terminals :: Serial
Classifier: Topic :: Home Automation
Classifier: Framework :: AsyncIO
Classifier: Development Status :: 4 - Beta
Requires-Python: >=3.9
License-File: LICENSE
Requires-Dist: pyserial>=3.4
Requires-Dist: pyserial-asyncio-fast>=0.11
Dynamic: author
Dynamic: classifier
Dynamic: description
Dynamic: description-content-type
Dynamic: home-page
Dynamic: license-file
Dynamic: requires-dist
Dynamic: requires-python
Dynamic: summary
